AUTHORS.rst
CHANGELOG.rst
LICENSE
MANIFEST.in
README.rst
setup.py
django_userprofile.egg-info/PKG-INFO
django_userprofile.egg-info/SOURCES.txt
django_userprofile.egg-info/dependency_links.txt
django_userprofile.egg-info/not-zip-safe
django_userprofile.egg-info/requires.txt
django_userprofile.egg-info/top_level.txt
userprofile/__init__.py
userprofile/admin.py
userprofile/forms.py
userprofile/models.py
userprofile/tests.py
userprofile/utils.py
userprofile/backends/__init__.py
userprofile/backends/simple/__init__.py
userprofile/backends/simple/urls.py
userprofile/fixtures/photosizes.json
userprofile/templates/userprofile/inclusion_tags/avatar.html
userprofile/templatetags/__init__.py
userprofile/templatetags/profile_inclusion_tags.py